{"inkVersion":20,"root":[[{"->":"Introduction"},["done",{"#f":5,"#n":"g-0"}],null],"done",{"Introduction":[{"->":".^.Start"},{"Start":[["^Good morning, you are already awake and dressed.","\n","^You're sitting by your favorite window with a mug in your hands, taking in the day.","\n",["ev",{"^->":"Introduction.Start.0.4.$r1"},{"temp=":"$r"},"str",{"->":".^.s"},[{"#n":"$r1"}],"/str","/ev",{"*":".^.^.c-0","flg":18},{"s":["^Look out the window ",{"->":"$r","var":true},null]}],{"c-0":["ev",{"^->":"Introduction.Start.0.c-0.$r2"},"/ev",{"temp=":"$r"},{"->":".^.^.4.s"},[{"#n":"$r2"}],{"->":"window"},"\n",{"#f":5}]}],{"#f":1}],"#f":1}],"window":[[["ev","visit",4,"MIN","du",4,"==",{"->":".^.10","c":true},4,"seq","nop","/ev","ev","du",0,"==","/ev",{"->":".^.s0","c":true},"ev","du",1,"==","/ev",{"->":".^.s1","c":true},"ev","du",2,"==","/ev",{"->":".^.s2","c":true},"ev","du",3,"==","/ev",{"->":".^.s3","c":true},"ev","du",4,"==","/ev",{"->":".^.s4","c":true},"nop",{"s0":["pop","\n","^You see a quiet weekend morning in early summer.","\n","ev",{"VAR?":"Season"},{"VAR?":"summer"},"+",{"VAR=":"Season","re":true},"/ev",{"#":"season 0"},{"->":".^.^.42"},null],"s1":["pop","\n","^You see a quiet weekend morning in early winter.","\n","ev",{"VAR?":"Season"},{"VAR?":"winter"},"+",{"VAR=":"Season","re":true},"/ev",{"#":"season 1"},{"->":".^.^.42"},null],"s2":["pop","\n","^You see a quiet weekend morning in early autumn.","\n","ev",{"VAR?":"Season"},{"VAR?":"autumn"},"+",{"VAR=":"Season","re":true},"/ev",{"#":"season 2"},{"->":".^.^.42"},null],"s3":["pop","\n","^You see a quiet weekend morning in early spring.","\n","ev",{"VAR?":"Season"},{"VAR?":"spring"},"+",{"VAR=":"Season","re":true},"/ev",{"#":"season 3"},{"->":".^.^.42"},null],"s4":["pop",{"->":".^.^.42"},null],"#f":5}],"\n",["ev","visit",3,"MIN","du",3,"==",{"->":".^.10","c":true},3,"seq","nop","/ev","ev","du",0,"==","/ev",{"->":".^.s0","c":true},"ev","du",1,"==","/ev",{"->":".^.s1","c":true},"ev","du",2,"==","/ev",{"->":".^.s2","c":true},"ev","du",3,"==","/ev",{"->":".^.s3","c":true},"nop",{"s0":["pop","\n","^It's quite sunny today.","\n","ev",{"VAR?":"Weather"},{"VAR?":"sunny"},"+",{"VAR=":"Weather","re":true},"/ev",{"#":"weather 0"},{"->":".^.^.36"},null],"s1":["pop","\n","^It's quite cloudy today.","\n","ev",{"VAR?":"Weather"},{"VAR?":"cloudy"},"+",{"VAR=":"Weather","re":true},"/ev",{"#":"weather 1"},{"->":".^.^.36"},null],"s2":["pop","\n","^It's quite wet today","\n","ev",{"VAR?":"Weather"},{"VAR?":"wet"},"+",{"VAR=":"Weather","re":true},"/ev",{"#":"weather 2"},{"->":".^.^.36"},null],"s3":["pop",{"->":".^.^.36"},null],"#f":5}],"\n",["ev",{"^->":"window.0.4.$r1"},{"temp=":"$r"},"str",{"->":".^.s"},[{"#n":"$r1"}],"/str","/ev",{"*":".^.^.c-0","flg":18},{"s":["^Take a sip from your mug ",{"->":"$r","var":true},null]}],{"c-0":["ev",{"^->":"window.0.c-0.$r2"},"/ev",{"temp=":"$r"},{"->":".^.^.4.s"},[{"#n":"$r2"}],{"->":"mug"},"\n",{"#f":5}]}],{"#f":1}],"mug":[["^What do you taste?","\n",["ev",{"^->":"mug.0.2.$r1"},{"temp=":"$r"},"str",{"->":".^.s"},[{"#n":"$r1"}],"/str","/ev",{"*":".^.^.c-0","flg":18},{"s":["^Coffee",{"->":"$r","var":true},null]}],["ev",{"^->":"mug.0.3.$r1"},{"temp=":"$r"},"str",{"->":".^.s"},[{"#n":"$r1"}],"/str","/ev",{"*":".^.^.c-1","flg":18},{"s":["^Tea",{"->":"$r","var":true},null]}],{"c-0":["ev",{"^->":"mug.0.c-0.$r2"},"/ev",{"temp=":"$r"},{"->":".^.^.2.s"},[{"#n":"$r2"}],"\n",{"#":"morningdrink 0"},"^It's bitter and vibrant on your tongue.","\n",{"->":".^.^.g-0"},{"#f":5}],"c-1":["ev",{"^->":"mug.0.c-1.$r2"},"/ev",{"temp=":"$r"},{"->":".^.^.3.s"},[{"#n":"$r2"}],"\n",{"#":"morningdrink 1"},"^The aroma hugs your face every time you approach the mug.","\n",[["^The brew turned out well this morning.","\n",{"->":"mug.0.g-0"},{"#f":5,"#n":"g-0"}],null],{"#f":5}],"g-0":["^Did you hear something?","\n",["ev",{"^->":"mug.0.g-0.2.$r1"},{"temp=":"$r"},"str",{"->":".^.s"},[{"#n":"$r1"}],"/str","/ev",{"*":".^.^.c-2","flg":18},{"s":["^Turn your head towards the sound",{"->":"$r","var":true},null]}],["ev",{"^->":"mug.0.g-0.3.$r1"},{"temp=":"$r"},"str",{"->":".^.s"},[{"#n":"$r1"}],"/str","/ev",{"*":".^.^.c-3","flg":18},{"s":["^Wait for the sound again",{"->":"$r","var":true},null]}],{"c-2":["ev",{"^->":"mug.0.g-0.c-2.$r2"},"/ev",{"temp=":"$r"},{"->":".^.^.2.s"},[{"#n":"$r2"}],"\n","^It's coming from the back door.","\n",{"->":"mug.0.g-1"},{"#f":5}],"c-3":["ev",{"^->":"mug.0.g-0.c-3.$r2"},"/ev",{"temp=":"$r"},{"->":".^.^.3.s"},[{"#n":"$r2"}],"\n","^You know that sound!","\n",{"->":"mug.0.g-1"},{"#f":5}],"#f":5}],"g-1":["^You feel giddy, excited, warm.","\n",{"->":"Names.Start"},{"#f":5}]}],{"#f":1}],"Names":[{"->":".^.Start"},{"Start":[["^You put your mug aside and hoist yourself out of the chair towards the back door.","\n","^What name do you hear?","\n",["ev",{"^->":"Names.Start.0.4.$r1"},{"temp=":"$r"},"str",{"->":".^.s"},[{"#n":"$r1"}],"/str","/ev",{"*":".^.^.c-0","flg":18},{"s":["^Gamma",{"->":"$r","var":true},null]}],["ev",{"^->":"Names.Start.0.5.$r1"},{"temp=":"$r"},"str",{"->":".^.s"},[{"#n":"$r1"}],"/str","/ev",{"*":".^.^.c-1","flg":18},{"s":["^Babcui",{"->":"$r","var":true},null]}],["ev",{"^->":"Names.Start.0.6.$r1"},{"temp=":"$r"},"str",{"->":".^.s"},[{"#n":"$r1"}],"/str","/ev",{"*":".^.^.c-2","flg":18},{"s":["^Nana",{"->":"$r","var":true},null]}],["ev",{"^->":"Names.Start.0.7.$r1"},{"temp=":"$r"},"str",{"->":".^.s"},[{"#n":"$r1"}],"/str","/ev",{"*":".^.^.c-3","flg":18},{"s":["^Grandma",{"->":"$r","var":true},null]}],["ev",{"^->":"Names.Start.0.8.$r1"},{"temp=":"$r"},"str",{"->":".^.s"},[{"#n":"$r1"}],"/str","/ev",{"*":".^.^.c-4","flg":18},{"s":["^Ga",{"->":"$r","var":true},null]}],{"c-0":["ev",{"^->":"Names.Start.0.c-0.$r2"},"/ev",{"temp=":"$r"},{"->":".^.^.4.s"},[{"#n":"$r2"}],"\n","ev",{"VAR?":"GrandmaName"},{"VAR?":"Gamma"},"+",{"VAR=":"GrandmaName","re":true},"/ev",{"#":"name 0"},{"->":".^.^.g-0"},{"#f":5}],"c-1":["ev",{"^->":"Names.Start.0.c-1.$r2"},"/ev",{"temp=":"$r"},{"->":".^.^.5.s"},[{"#n":"$r2"}],"\n","ev",{"VAR?":"GrandmaName"},{"VAR?":"Babcui"},"+",{"VAR=":"GrandmaName","re":true},"/ev",{"#":"name 1"},{"->":".^.^.g-0"},{"#f":5}],"c-2":["ev",{"^->":"Names.Start.0.c-2.$r2"},"/ev",{"temp=":"$r"},{"->":".^.^.6.s"},[{"#n":"$r2"}],"\n","ev",{"VAR?":"GrandmaName"},{"VAR?":"Nana"},"+",{"VAR=":"GrandmaName","re":true},"/ev",{"#":"name 2"},{"->":".^.^.g-0"},{"#f":5}],"c-3":["ev",{"^->":"Names.Start.0.c-3.$r2"},"/ev",{"temp=":"$r"},{"->":".^.^.7.s"},[{"#n":"$r2"}],"\n","ev",{"VAR?":"GrandmaName"},{"VAR?":"Grandma"},"+",{"VAR=":"GrandmaName","re":true},"/ev",{"#":"name 3"},{"->":".^.^.g-0"},{"#f":5}],"c-4":["ev",{"^->":"Names.Start.0.c-4.$r2"},"/ev",{"temp=":"$r"},{"->":".^.^.8.s"},[{"#n":"$r2"}],"\n","ev",{"VAR?":"GrandmaName"},{"VAR?":"Ga"},"+",{"VAR=":"GrandmaName","re":true},"/ev",{"#":"name 4"},{"->":".^.^.g-0"},{"#f":5}],"g-0":["^\"","ev",{"VAR?":"GrandmaName"},"out","/ev","^!\" your beloved grandchild screams, bouncing into the room.","\n",{"->":"Names.Grandchildname"},{"#f":5}]}],{"#f":1}],"Grandchildname":[["^What do you call your grandchild?","\n",["ev",{"^->":"Names.Grandchildname.0.2.$r1"},{"temp=":"$r"},"str",{"->":".^.s"},[{"#n":"$r1"}],"/str","/ev",{"*":".^.^.c-0","flg":18},{"s":["^Munch",{"->":"$r","var":true},null]}],["ev",{"^->":"Names.Grandchildname.0.3.$r1"},{"temp=":"$r"},"str",{"->":".^.s"},[{"#n":"$r1"}],"/str","/ev",{"*":".^.^.c-1","flg":18},{"s":["^Bean",{"->":"$r","var":true},null]}],["ev",{"^->":"Names.Grandchildname.0.4.$r1"},{"temp=":"$r"},"str",{"->":".^.s"},[{"#n":"$r1"}],"/str","/ev",{"*":".^.^.c-2","flg":18},{"s":["^Mousie",{"->":"$r","var":true},null]}],{"c-0":["ev",{"^->":"Names.Grandchildname.0.c-0.$r2"},"/ev",{"temp=":"$r"},{"->":".^.^.2.s"},[{"#n":"$r2"}],"\n",{"#":"petname 0"},"ev",{"VAR?":"Petname"},{"VAR?":"Munch"},"+",{"VAR=":"Petname","re":true},"/ev",{"->":".^.^.g-0"},{"#f":5}],"c-1":["ev",{"^->":"Names.Grandchildname.0.c-1.$r2"},"/ev",{"temp=":"$r"},{"->":".^.^.3.s"},[{"#n":"$r2"}],"\n",{"#":"petname 1"},"ev",{"VAR?":"Petname"},{"VAR?":"Bean"},"+",{"VAR=":"Petname","re":true},"/ev",{"->":".^.^.g-0"},{"#f":5}],"c-2":["ev",{"^->":"Names.Grandchildname.0.c-2.$r2"},"/ev",{"temp=":"$r"},{"->":".^.^.4.s"},[{"#n":"$r2"}],"\n",{"#":"petname 2"},"ev",{"VAR?":"Petname"},{"VAR?":"Mousie"},"+",{"VAR=":"Petname","re":true},"/ev",{"->":".^.^.g-0"},{"#f":5}],"g-0":["^\"I am so happy to see you, ","ev",{"VAR?":"Petname"},"out","/ev","^!\"","\n","^\"","ev",{"VAR?":"GrandmaName"},"out","/ev","^, ","ev",{"VAR?":"GrandmaName"},"out","/ev","^, what are we going to do today?\" they ask.","\n","^You quickly wave out the window and shut the door. You marvel that this creaky old place can still contain the excitement of a young child.","\n",{"->":"Snack"},{"#f":5}]}],{"#f":1}],"#f":1}],"Snack":[{"->":".^.Start"},{"Start":[["^\"Let's get you a snack first. Did you eat yet?\"","\n","^Your grandchild sighs and flops their arms around in protest.","\n",["ev",{"^->":"Snack.Start.0.4.$r1"},{"temp=":"$r"},"str",{"->":".^.s"},[{"#n":"$r1"}],"/str","/ev",{"*":".^.^.c-0","flg":18},{"s":["^\"I'll make your favorite.\"",{"->":"$r","var":true},null]}],{"c-0":["ev",{"^->":"Snack.Start.0.c-0.$r2"},"/ev",{"temp=":"$r"},{"->":".^.^.4.s"},[{"#n":"$r2"}],"\n","^\"Do you remember my favorite?\"","\n",[["ev",{"^->":"Snack.Start.0.c-0.9.0.$r1"},{"temp=":"$r"},"str",{"->":".^.s"},[{"#n":"$r1"}],"/str","/ev",{"*":".^.^.c-0","flg":18},{"s":["^\"Of course I do!\" ",{"->":"$r","var":true},null]}],["ev",{"^->":"Snack.Start.0.c-0.9.1.$r1"},{"temp=":"$r"},"str",{"->":".^.s"},[{"#n":"$r1"}],"/str","/ev",{"*":".^.^.c-1","flg":18},{"s":["^\"Let me think.\"",{"->":"$r","var":true},null]}],{"c-0":["ev",{"^->":"Snack.Start.0.c-0.9.c-0.$r2"},"/ev",{"temp=":"$r"},{"->":".^.^.0.s"},[{"#n":"$r2"}],"\n","^You put your hands on your hips and straighten up.","\n",{"->":".^.^.^.^.g-0"},{"#f":5}],"c-1":["ev",{"^->":"Snack.Start.0.c-0.9.c-1.$r2"},"/ev",{"temp=":"$r"},{"->":".^.^.1.s"},[{"#n":"$r2"}],"\n","^You tap your finger on your chin.","\n",{"->":".^.^.^.^.g-0"},{"#f":5}]}],{"#f":5}],"g-0":["^\"Your favorite snack is...","\n",[["ev",{"^->":"Snack.Start.0.g-0.2.0.$r1"},{"temp=":"$r"},"str",{"->":".^.s"},[{"#n":"$r1"}],"/str","/ev",{"*":".^.^.c-0","flg":18},{"s":["^...peanut butter celery sticks.\"",{"->":"$r","var":true},null]}],["ev",{"^->":"Snack.Start.0.g-0.2.1.$r1"},{"temp=":"$r"},"str",{"->":".^.s"},[{"#n":"$r1"}],"/str","/ev",{"*":".^.^.c-1","flg":18},{"s":["^...apple slices.\"",{"->":"$r","var":true},null]}],["ev",{"^->":"Snack.Start.0.g-0.2.2.$r1"},{"temp=":"$r"},"str",{"->":".^.s"},[{"#n":"$r1"}],"/str","/ev",{"*":".^.^.c-2","flg":18},{"s":["^...rye bread with lots of butter.\"",{"->":"$r","var":true},null]}],["ev",{"^->":"Snack.Start.0.g-0.2.3.$r1"},{"temp=":"$r"},"str",{"->":".^.s"},[{"#n":"$r1"}],"/str","/ev",{"*":".^.^.c-3","flg":18},{"s":["^...chocolate chip cookies.\"",{"->":"$r","var":true},null]}],{"c-0":["ev",{"^->":"Snack.Start.0.g-0.2.c-0.$r2"},"/ev",{"temp=":"$r"},{"->":".^.^.0.s"},[{"#n":"$r2"}],"\n",{"#":"snack 0"},"^The child scrunches their face, waiting.","\n","^\"With NO raisins because they're gross.\" You add, poking their nose.","\n",{"->":".^.^.g-0"},{"#f":5}],"c-1":["ev",{"^->":"Snack.Start.0.g-0.2.c-1.$r2"},"/ev",{"temp=":"$r"},{"->":".^.^.1.s"},[{"#n":"$r2"}],"\n",{"#":"snack 1"},"^Their expression softened into a smile.","\n",{"->":".^.^.g-0"},{"#f":5}],"c-2":["ev",{"^->":"Snack.Start.0.g-0.2.c-2.$r2"},"/ev",{"temp=":"$r"},{"->":".^.^.2.s"},[{"#n":"$r2"}],"\n",{"#":"snack 2"},"^\"Is it ","ev",{"VAR?":"GrandmaName"},"out","/ev","^ bread?\" they ask.","\n","^\"Of course it is! You know I make bread every week.\"","\n",{"->":".^.^.g-0"},{"#f":5}],"c-3":["ev",{"^->":"Snack.Start.0.g-0.2.c-3.$r2"},"/ev",{"temp=":"$r"},{"->":".^.^.3.s"},[{"#n":"$r2"}],"\n",{"#":"snack 3"},"^Immediately the child's eyes lock on to the direction of the cookie jar.","\n",{"->":".^.^.g-0"},{"#f":5}],"g-0":["^You hear the low gurgle of a hungry tummy.","\n",["ev",{"^->":"Snack.Start.0.g-0.2.g-0.2.$r1"},{"temp=":"$r"},"str",{"->":".^.s"},[{"#n":"$r1"}],"/str","/ev",{"*":".^.^.c-4","flg":18},{"s":["^\"Do you remember what we need to do before snack time?\"",{"->":"$r","var":true},null]}],{"c-4":["ev",{"^->":"Snack.Start.0.g-0.2.g-0.c-4.$r2"},"/ev",{"temp=":"$r"},{"->":".^.^.2.s"},[{"#n":"$r2"}],"\n",{"->":"Snack.KitchenSnack"},{"#f":5}],"#f":5}]}],{"#f":5}]}],{"#f":1}],"KitchenSnack":["^\"Wash our hands?\"","\n","^\"Exactly right. Come on now, into the kitchen.\"","\n","^They run ahead of you.","\n","^And so began your day. ",{"->":"Interlude.Start"},"\n",{"#f":1}],"#f":1}],"Interlude":[{"->":".^.Start"},{"Start":[[["ev",{"^->":"Interlude.Start.0.0.$r1"},{"temp=":"$r"},"str",{"->":".^.s"},[{"#n":"$r1"}],"/str","/ev",{"*":".^.^.c-0","flg":18},{"s":["^What a busy day!",{"->":"$r","var":true},null]}],["ev",{"^->":"Interlude.Start.0.1.$r1"},{"temp=":"$r"},"str",{"->":".^.s"},[{"#n":"$r1"}],"/str","/ev",{"*":".^.^.c-1","flg":18},{"s":["^What a cozy day.",{"->":"$r","var":true},null]}],["ev",{"^->":"Interlude.Start.0.2.$r1"},{"temp=":"$r"},"str",{"->":".^.s"},[{"#n":"$r1"}],"/str","/ev",{"*":".^.^.c-2","flg":18},{"s":["^What a calming day.",{"->":"$r","var":true},null]}],{"c-0":["ev",{"^->":"Interlude.Start.0.c-0.$r2"},"/ev",{"temp=":"$r"},{"->":".^.^.0.s"},[{"#n":"$r2"}],"\n","^You two were all over the house and back yard, looking at anything and everything. Things you considered chores around the house were new adventures for the child. A constant flow of conversation stitched the locations together. Whew! Your doctor would be impressed if you had one of those fit-watch-things whatever they're called.","\n",{"->":".^.^.g-0"},{"#f":5}],"c-1":["ev",{"^->":"Interlude.Start.0.c-1.$r2"},"/ev",{"temp=":"$r"},{"->":".^.^.1.s"},[{"#n":"$r2"}],"\n","^You had your snack and did some crafts before making dinner. Every so often your grandchild wanted cuddles which you were more than happy to give.","\n",{"->":".^.^.g-0"},{"#f":5}],"c-2":["ev",{"^->":"Interlude.Start.0.c-2.$r2"},"/ev",{"temp=":"$r"},{"->":".^.^.2.s"},[{"#n":"$r2"}],"\n","^You made a snack which evened out your grandchild's energy. You didn't do much besides work on a puzzle with the TV on in the other room, but it was just what you two needed.","\n",{"->":".^.^.g-0"},{"#f":5}],"g-0":[["ev",{"^->":"Interlude.Start.0.g-0.0.$r1"},{"temp=":"$r"},"str",{"->":".^.s"},[{"#n":"$r1"}],"/str","/ev",{"*":".^.^.c-3","flg":18},{"s":["^Oh wow, is <i>that</i> the time?...",{"->":"$r","var":true},null]}],{"c-3":["ev",{"^->":"Interlude.Start.0.g-0.c-3.$r2"},"/ev",{"temp=":"$r"},{"->":".^.^.0.s"},[{"#n":"$r2"}],"\n",{"->":"Memory.Start"},{"#f":5}],"#f":5}]}],{"#f":1}],"#f":1}],"Memory":[{"->":".^.Start"},{"Start":[["^It's getting late for ","ev",{"VAR?":"GrandmaName"},"out","/ev","^s. You feel yourself sinking into your favorite armchair.","\n","^Your eyes soften.","\n","^And close...","\n",["ev",{"^->":"Memory.Start.0.11.$r1"},{"temp=":"$r"},"str",{"->":".^.s"},[{"#n":"$r1"}],"/str","/ev",{"*":".^.^.c-0","flg":18},{"s":["^Maybe just a couple minutes.",{"->":"$r","var":true},null]}],["ev",{"^->":"Memory.Start.0.12.$r1"},{"temp=":"$r"},"str",{"->":".^.s"},[{"#n":"$r1"}],"/str","/ev",{"*":".^.^.c-1","flg":18},{"s":["^What's that sound?",{"->":"$r","var":true},null]}],{"c-0":["ev",{"^->":"Memory.Start.0.c-0.$r2"},"/ev",{"temp=":"$r"},{"->":".^.^.11.s"},[{"#n":"$r2"}],"\n","^The soft cushioning of your chair","\n","^\"Heyyy it's not sleep time yet!\"","\n","^You open your eyes and see your grandchild's face an inch from yours. Your sleeve is balled up in their small fist.","\n","^\"I'm sorry, what were you saying?\"","\n",{"->":".^.^.g-0"},{"#f":5}],"c-1":["ev",{"^->":"Memory.Start.0.c-1.$r2"},"/ev",{"temp=":"$r"},{"->":".^.^.12.s"},[{"#n":"$r2"}],"\n","^You crack one eyelid open and yawn.","\n","^\"I'm awake,\" you say on reflex.","\n","^Your grandchild waits for you sit up straight again before repeating their question.","\n","^There's a small melancholy that comes with realizing your grandchild is old enough to see your age.","\n",{"->":".^.^.g-0"},{"#f":5}],"g-0":["^\"","ev",{"VAR?":"GrandmaName"},"out","/ev","^, what's this?\"","\n","^They're holding a picture frame. You have to blink a couple time and angle your head to see it.","\n","^What did they bring you?","\n",["ev",{"^->":"Memory.Start.0.g-0.11.$r1"},{"temp=":"$r"},"str",{"->":".^.s"},[{"#n":"$r1"}],"/str","/ev",{"*":".^.^.c-2","flg":18},{"s":["^Your diploma.",{"->":"$r","var":true},null]}],["ev",{"^->":"Memory.Start.0.g-0.12.$r1"},{"temp=":"$r"},"str",{"->":".^.s"},[{"#n":"$r1"}],"/str","/ev",{"*":".^.^.c-3","flg":18},{"s":["^A picture of a protest.",{"->":"$r","var":true},null]}],["ev",{"^->":"Memory.Start.0.g-0.13.$r1"},{"temp=":"$r"},"str",{"->":".^.s"},[{"#n":"$r1"}],"/str","/ev",{"*":".^.^.c-4","flg":18},{"s":["^A photo of Japan.",{"->":"$r","var":true},null]}],{"c-2":["ev",{"^->":"Memory.Start.0.g-0.c-2.$r2"},"/ev",{"temp=":"$r"},{"->":".^.^.11.s"},[{"#n":"$r2"}],"\n",{"#":"memory 0"},"^\"Oh that's my diploma for when I finished school.\"","\n","^You smile at your name nestled among ostentateous latin.","\n","^\"How long did you have to do school, ","ev",{"VAR?":"GrandmaName"},"out","/ev","^?\"","\n","^\"Well...","\n",[["ev",{"^->":"Memory.Start.0.g-0.c-2.21.0.$r1"},{"temp=":"$r"},"str",{"->":".^.s"},[{"#n":"$r1"}],"/str","/ev",{"*":".^.^.c-0","flg":18},{"s":["^I was the first in my family to graduate from college.\"",{"->":"$r","var":true},null]}],["ev",{"^->":"Memory.Start.0.g-0.c-2.21.1.$r1"},{"temp=":"$r"},"str",{"->":".^.s"},[{"#n":"$r1"}],"/str","/ev",{"*":".^.^.c-1","flg":18},{"s":["^I went to a trade school.\"",{"->":"$r","var":true},null]}],["ev",{"^->":"Memory.Start.0.g-0.c-2.21.2.$r1"},{"temp=":"$r"},"str",{"->":".^.s"},[{"#n":"$r1"}],"/str","/ev",{"*":".^.^.c-2","flg":18},{"s":["^I got my pHD\" ",{"->":"$r","var":true},null]}],{"c-0":["ev",{"^->":"Memory.Start.0.g-0.c-2.21.c-0.$r2"},"/ev",{"temp=":"$r"},{"->":".^.^.0.s"},[{"#n":"$r2"}],"\n","^\"So I guess that means I was in school for eighteen years or so! It was hard to be the first. But when the next one in our family went to college I could give them the advice I needed when I was young.\"","\n",{"->":".^.^.g-0"},{"#f":5}],"c-1":["ev",{"^->":"Memory.Start.0.g-0.c-2.21.c-1.$r2"},"/ev",{"temp=":"$r"},{"->":".^.^.1.s"},[{"#n":"$r2"}],"\n","^\"So that means I finished up high school and then spent a couple years to get really good at my job before I started working. It was still school, but it was the first time school taught me what I really wanted to learn.\"","\n",{"->":".^.^.g-0"},{"#f":5}],"c-2":["ev",{"^->":"Memory.Start.0.g-0.c-2.21.c-2.$r2"},"/ev",{"temp=":"$r"},{"->":".^.^.2.s"},[{"#n":"$r2"}],"\n","^\"And that took forever! I worked really hard in school for around twenty, maybe twenty five years? It blurs together, but I was so proud when I graduated and got to call myself a doctor.\"","\n",{"->":".^.^.g-0"},{"#f":5}],"g-0":["^Your grandchild groans.","\n","^\"That's so long...\"","\n",["ev",{"^->":"Memory.Start.0.g-0.c-2.21.g-0.4.$r1"},{"temp=":"$r"},"str",{"->":".^.s"},[{"#n":"$r1"}],"/str","/ev",{"*":".^.^.c-3","flg":18},{"s":["^It is",{"->":"$r","var":true},null]}],["ev",{"^->":"Memory.Start.0.g-0.c-2.21.g-0.5.$r1"},{"temp=":"$r"},"str",{"->":".^.s"},[{"#n":"$r1"}],"/str","/ev",{"*":".^.^.c-4","flg":18},{"s":["^Not really",{"->":"$r","var":true},null]}],{"c-3":["ev",{"^->":"Memory.Start.0.g-0.c-2.21.g-0.c-3.$r2"},"/ev",{"temp=":"$r"},{"->":".^.^.4.s"},[{"#n":"$r2"}],"\n","^\"You never stop learning as long as you live, but school does end eventually.","\n",{"->":".^.^.^.g-1"},{"#f":5}],"c-4":["ev",{"^->":"Memory.Start.0.g-0.c-2.21.g-0.c-4.$r2"},"/ev",{"temp=":"$r"},{"->":".^.^.5.s"},[{"#n":"$r2"}],"\n","^\"It goes by much faster than you think because you're so busy.","\n",{"->":".^.^.^.g-1"},{"#f":5}],"#f":5}],"g-1":["^\"Don't worry too much about it - you have a good head on your shoulders.\" ",{"->":"Memory.SummingUp"},"\n",{"#f":5}]}],{"#f":5}],"c-3":["ev",{"^->":"Memory.Start.0.g-0.c-3.$r2"},"/ev",{"temp=":"$r"},{"->":".^.^.12.s"},[{"#n":"$r2"}],"\n",{"#":"memory 1"},"^\"That's a newspaper clipping of a protest I went to when I was a little younger than your parent.\"","\n","^\"What's a protest?\"","\n",[["ev",{"^->":"Memory.Start.0.g-0.c-3.12.0.$r1"},{"temp=":"$r"},"str",{"->":".^.s"},[{"#n":"$r1"}],"/str","/ev",{"*":".^.^.c-0","flg":18},{"s":["^Answer truthfully",{"->":"$r","var":true},null]}],["ev",{"^->":"Memory.Start.0.g-0.c-3.12.1.$r1"},{"temp=":"$r"},"str",{"->":".^.s"},[{"#n":"$r1"}],"/str","/ev",{"*":".^.^.c-1","flg":18},{"s":["^Deflect respectfully",{"->":"$r","var":true},null]}],{"c-0":["ev",{"^->":"Memory.Start.0.g-0.c-3.12.c-0.$r2"},"/ev",{"temp=":"$r"},{"->":".^.^.0.s"},[{"#n":"$r2"}],"\n","^\"It's when people who believe in something get together in a big group and show the people in charge that what they believe in is important and must be respected.\"","\n",{"->":".^.^.g-0"},{"#f":5}],"c-1":["ev",{"^->":"Memory.Start.0.g-0.c-3.12.c-1.$r2"},"/ev",{"temp=":"$r"},{"->":".^.^.1.s"},[{"#n":"$r2"}],"\n","^\"I'm not sure how to explain it right now,\" you tell them, \"But I'll think on it and when I know I'll tell you.\"","\n",{"->":".^.^.g-0"},{"#f":5}],"g-0":["^Your grandchild nods and looks at the clipping again.","\n",["^\"What was it like?\"","\n",["ev",{"^->":"Memory.Start.0.g-0.c-3.12.g-0.g-1.2.$r1"},{"temp=":"$r"},"str",{"->":".^.s"},[{"#n":"$r1"}],"/str","/ev",{"*":".^.^.c-2","flg":18},{"s":["^Talk about how it looked",{"->":"$r","var":true},null]}],["ev",{"^->":"Memory.Start.0.g-0.c-3.12.g-0.g-1.3.$r1"},{"temp=":"$r"},"str",{"->":".^.s"},[{"#n":"$r1"}],"/str","/ev",{"*":".^.^.c-3","flg":18},{"s":["^Talk about how it felt",{"->":"$r","var":true},null]}],["ev",{"^->":"Memory.Start.0.g-0.c-3.12.g-0.g-1.4.$r1"},{"temp=":"$r"},"str",{"->":".^.s"},[{"#n":"$r1"}],"/str","/ev",{"*":".^.^.c-4","flg":18},{"s":["^I'm not ready to talk about it...",{"->":"$r","var":true},null]}],{"c-2":["ev",{"^->":"Memory.Start.0.g-0.c-3.12.g-0.g-1.c-2.$r2"},"/ev",{"temp=":"$r"},{"->":".^.^.2.s"},[{"#n":"$r2"}],"\n","^\"There were so many people - people everywhere I looked. Many had signs, some of them silly and some of them very serious. We listened to speakers and sang protest songs together.\" You're leaving things out but your grandchild doesn't seem to notice.","\n",{"->":".^.^.^.^.g-2"},{"#f":5}],"c-3":["ev",{"^->":"Memory.Start.0.g-0.c-3.12.g-0.g-1.c-3.$r2"},"/ev",{"temp=":"$r"},{"->":".^.^.3.s"},[{"#n":"$r2"}],"\n","^\"It's was beautiful, exciting, empowering. And scary. And tiring.\"","\n",{"->":".^.^.^.^.g-2"},{"#f":5}],"c-4":["ev",{"^->":"Memory.Start.0.g-0.c-3.12.g-0.g-1.c-4.$r2"},"/ev",{"temp=":"$r"},{"->":".^.^.4.s"},[{"#n":"$r2"}],"\n","^\"I'm sorry ","ev",{"VAR?":"Petname"},"out","/ev","^.\"","\n","^You look down at the yellowing newsprint.","\n","^\"It's a memory that's hard to talk about, even though it's really important to me.\"","\n",[["ev",{"^->":"Memory.Start.0.g-0.c-3.12.g-0.g-1.c-4.18.0.$r1"},{"temp=":"$r"},"str",{"->":".^.s"},[{"#n":"$r1"}],"/str","/ev",{"*":".^.^.c-0","flg":18},{"s":["^\"Do you understand?\"",{"->":"$r","var":true},null]}],["ev",{"^->":"Memory.Start.0.g-0.c-3.12.g-0.g-1.c-4.18.1.$r1"},{"temp=":"$r"},"str",{"->":".^.s"},[{"#n":"$r1"}],"/str","/ev",{"*":".^.^.c-1","flg":18},{"s":["^\"I promise I'll tell you later.\" ",{"->":"$r","var":true},null]}],{"c-0":["ev",{"^->":"Memory.Start.0.g-0.c-3.12.g-0.g-1.c-4.18.c-0.$r2"},"/ev",{"temp=":"$r"},{"->":".^.^.0.s"},[{"#n":"$r2"}],"\n","^\"Not really...\"","\n","^They look down at the frame with a droop to their frame.","\n","^\"That's ok, and ","ev",{"VAR?":"Petname"},"out","/ev","^ - you did nothing wrong for asking me. Thank you for giving me time.\"","\n",{"->":".^.^.^.^.^.^.g-2"},{"#f":5}],"c-1":["ev",{"^->":"Memory.Start.0.g-0.c-3.12.g-0.g-1.c-4.18.c-1.$r2"},"/ev",{"temp=":"$r"},{"->":".^.^.1.s"},[{"#n":"$r2"}],"\n","^\"You promise?\"","\n","^\"I <i>promise</i>.\"","\n","^\"It's not because I'm too little?\"","\n","^\"No, I'm just not ready. But one day I will be. For you.\"","\n",{"->":".^.^.^.^.^.^.g-2"},{"#f":5}]}],{"#f":5}],"#f":5,"#n":"g-1"}],{"#f":5}],"g-2":[{"->":"Memory.SummingUp"},{"#f":5}]}],{"#f":5}],"c-4":["ev",{"^->":"Memory.Start.0.g-0.c-4.$r2"},"/ev",{"temp=":"$r"},{"->":".^.^.13.s"},[{"#n":"$r2"}],"\n",{"#":"memory 2"},"^\"That's a photo of me when I went to Japan.\"","\n","^\"Where's that?\"","\n","^\"It's a bunch of islands in the Pacific Ocean, by China and Korea.\"","\n",[["ev",{"^->":"Memory.Start.0.g-0.c-4.14.0.$r1"},{"temp=":"$r"},"str",{"->":".^.s"},[{"#n":"$r1"}],"/str","/ev",{"*":".^.^.c-0","flg":18},{"s":["^Talk about the food",{"->":"$r","var":true},null]}],["ev",{"^->":"Memory.Start.0.g-0.c-4.14.1.$r1"},{"temp=":"$r"},"str",{"->":".^.s"},[{"#n":"$r1"}],"/str","/ev",{"*":".^.^.c-1","flg":18},{"s":["^Talk about the trip",{"->":"$r","var":true},null]}],["ev",{"^->":"Memory.Start.0.g-0.c-4.14.2.$r1"},{"temp=":"$r"},"str",{"->":".^.s"},[{"#n":"$r1"}],"/str","/ev",{"*":".^.^.c-2","flg":18},{"s":["^Talk about the opportunity",{"->":"$r","var":true},null]}],{"c-0":["ev",{"^->":"Memory.Start.0.g-0.c-4.14.c-0.$r2"},"/ev",{"temp=":"$r"},{"->":".^.^.0.s"},[{"#n":"$r2"}],"\n","^\"The seafood there is so fresh because the water is right there. And the Japanese love to eat foods by the season. So if you travel there in April and then again in September, all the flavors will be different.\"","\n",{"->":".^.^.g-0"},{"#f":5}],"c-1":["ev",{"^->":"Memory.Start.0.g-0.c-4.14.c-1.$r2"},"/ev",{"temp=":"$r"},{"->":".^.^.1.s"},[{"#n":"$r2"}],"\n","^\"I took a couple airplanes to get there. It took a full day, but back before planes it would take months so I can't complain too much. And when you get there, you can take a train anywhere you like and they are always exactly on time.","\n",{"->":".^.^.g-0"},{"#f":5}],"c-2":["ev",{"^->":"Memory.Start.0.g-0.c-4.14.c-2.$r2"},"/ev",{"temp=":"$r"},{"->":".^.^.2.s"},[{"#n":"$r2"}],"\n","^\"When I was younger I wanted to travel all over the world, but that takes time and money so I had to be picky about where I went.","\n","^\"Is there anywhere you still want to go?\"","\n",[["ev",{"^->":"Memory.Start.0.g-0.c-4.14.c-2.11.0.$r1"},{"temp=":"$r"},"str",{"->":".^.s"},[{"#n":"$r1"}],"/str","/ev",{"*":".^.^.c-0","flg":18},{"s":["^Deflect",{"->":"$r","var":true},null]}],["ev",{"^->":"Memory.Start.0.g-0.c-4.14.c-2.11.1.$r1"},{"temp=":"$r"},"str",{"->":".^.s"},[{"#n":"$r1"}],"/str","/ev",{"*":".^.^.c-1","flg":18},{"s":["^Be honest",{"->":"$r","var":true},null]}],{"c-0":["ev",{"^->":"Memory.Start.0.g-0.c-4.14.c-2.11.c-0.$r2"},"/ev",{"temp=":"$r"},{"->":".^.^.0.s"},[{"#n":"$r2"}],"\n","^\"I want to go to your house for a sleepover.\"","\n","^\"","ev",{"VAR?":"GrandmaName"},"out","/ev","^!\"","\n","^\"","ev",{"VAR?":"Petname"},"out","/ev","^!\"","\n",{"->":".^.^.g-0"},{"#f":5}],"c-1":["ev",{"^->":"Memory.Start.0.g-0.c-4.14.c-2.11.c-1.$r2"},"/ev",{"temp=":"$r"},{"->":".^.^.1.s"},[{"#n":"$r2"}],"\n","^\"Oh, plenty.\" You pet your grandchild's hair.","\n","^\"But I'm too old now, so you better tell me all about where you go or I'll get jealous!\"","\n",{"->":".^.^.g-0"},{"#f":5}],"g-0":["^You catch your granchild's giggle, and they catch your yawn.","\n",{"->":".^.^.^.^.g-0"},{"#f":5}]}],{"#f":5}],"g-0":["^You glance at the clock.","\n",["ev",{"^->":"Memory.Start.0.g-0.c-4.14.g-0.2.$r1"},{"temp=":"$r"},"str",{"->":".^.s"},[{"#n":"$r1"}],"/str","/ev",{"*":".^.^.c-3","flg":18},{"s":["^It really is getting late. ",{"->":"$r","var":true},null]}],{"c-3":["ev",{"^->":"Memory.Start.0.g-0.c-4.14.g-0.c-3.$r2"},"/ev",{"temp=":"$r"},{"->":".^.^.2.s"},[{"#n":"$r2"}],{"->":"Memory.SummingUp"},"\n",{"#f":5}],"#f":5}]}],{"#f":5}],"#f":5}]}],{"#f":1}],"SummingUp":["^It's time for ","ev",{"VAR?":"GrandmaName"},"out","/ev","^s and ","ev",{"VAR?":"Petname"},"out","/ev","^s to think about going to bed.","\n",{"->":"EveningInterlude"},{"#f":1}],"#f":1}],"EveningInterlude":[["^The rest of your evening is quiet and cozy until your beloved ","ev",{"VAR?":"Petname"},"out","/ev","^ has to go.","\n","^You exchange hugs and promises to catch up with a very grateful and refreshed parent. You catch your grandchild's eye","\n",["ev",{"^->":"EveningInterlude.0.9.$r1"},{"temp=":"$r"},"str",{"->":".^.s"},[{"#n":"$r1"}],"/str","/ev",{"*":".^.^.c-0","flg":18},{"s":["^\"I love you, ","ev",{"VAR?":"Petname"},"out","/ev","^!\"",{"->":"$r","var":true},null]}],{"c-0":["ev",{"^->":"EveningInterlude.0.c-0.$r2"},"/ev",{"temp=":"$r"},{"->":".^.^.9.s"},[{"#n":"$r2"}],"\n",{"->":".^.^.g-0"},{"#f":5}],"g-0":["^\"I love you too, ","ev",{"VAR?":"GrandmaName"},"out","/ev","^!\"","\n","^The house is quiet and full.","\n",{"#":"end 0"},{"->":"Ending"},{"#f":5}]}],{"#f":1}],"Ending":[{"->":".^.Start"},{"Start":["^You made a wonderful memory today.","\n","end",{"#f":1}],"#f":1}],"global decl":["ev",{"list":{},"origins":["GrandmaName"]},{"VAR=":"GrandmaName"},{"list":{},"origins":["Petname"]},{"VAR=":"Petname"},{"list":{},"origins":["Weather"]},{"VAR=":"Weather"},{"list":{},"origins":["Season"]},{"VAR=":"Season"},"/ev","end",null],"#f":1}],"listDefs":{"GrandmaName":{"Gamma":1,"Babcui":2,"Nana":3,"Grandma":4,"Ga":5},"Petname":{"Munch":1,"Bean":2,"Mousie":3},"Weather":{"sunny":1,"cloudy":2,"wet":3},"Season":{"summer":1,"winter":2,"autumn":3,"spring":4}}}